<?xml version="1.0" encoding="utf-8" standalone="no"?>
<!DOCTYPE toc PUBLIC "-//Sun Microsystems Inc.//DTD JavaHelp TOC Version 1.0//EN" "http://java.sun.com/products/javahelp/toc_1_0.dtd">
<toc version="1.0">
<tocitem target="index" text="Game of Life of Conway">
<tocitem target="section_4193f95605e5652ef30dc18f4efa9dbf" text="Game of Life of Conway">
<tocitem target="concat" text="concat"/>
<tocitem target="conway" text="conway"/>
<tocitem target="evolution" text="evolution"/>
<tocitem target="genzero" text="genzero"/>
</tocitem>
</tocitem>
</toc>